azure/cli/command_modules/documentdb/__init__.py
azure/cli/command_modules/documentdb/_client_factory.py
azure/cli/command_modules/documentdb/_command_type.py
azure/cli/command_modules/documentdb/_exception_handler.py
azure/cli/command_modules/documentdb/_help.py
azure/cli/command_modules/documentdb/_params.py
azure/cli/command_modules/documentdb/commands.py
azure/cli/command_modules/documentdb/custom.py
azure_cli_documentdb-0.1.5.dist-info/DESCRIPTION.rst
azure_cli_documentdb-0.1.5.dist-info/METADATA
azure_cli_documentdb-0.1.5.dist-info/RECORD
azure_cli_documentdb-0.1.5.dist-info/WHEEL
azure_cli_documentdb-0.1.5.dist-info/metadata.json
azure_cli_documentdb-0.1.5.dist-info/top_level.txt
